{
	"吴大维": {
		"name": "吴大维",
		"P": 1,
		"holiday": 0,
		"email": ""
	},
	"沈志敏": {
		"name": "沈志敏",
		"P": 3,
		"holiday": 0,
		"email": "zhimin.shen@baoz.cn"
	},
	"beaver": {
		"name": "蔡成龙",
		"P": 3,
		"holiday": 0,
		"email": "chenglong.cai@baoz.cn"
	},
	"周瀚": {
		"name": "周瀚",
		"P": 3,
		"holiday": 0,
		"email": "han.zhou@baoz.cn"
	},
	"魏显龙": {
		"name": "魏显龙",
		"P": 3,
		"holiday": 0,
		"email": "xianlong.wei@baoz.cn"
	},
	"且听风殇": {
		"name": "杨丛聿",
		"P": 3,
		"holiday": 0,
		"email": "congyu.yang@baoz.cn"
	},
	"孙培奇": {
		"name": "孙培奇",
		"P": 2,
		"holiday": 0,
		"email": "peiqi.sun@baoz.cn"
	},
	"房星星": {
		"name": "房星星",
		"P": 2,
		"holiday": 0,
		"email": "xingxing.fang@baoz.cn"
	},
	"庄梦秋": {
		"name": "庄梦秋",
		"P": 3,
		"holiday": 0,
		"email": "mengqiu.zhuang@baoz.cn"
	},
	"李文杰": {
		"name": "李文杰",
		"P": 2,
		"holiday": 0,
		"email": "wenjie.li@baoz.cn"
	},
	"王慕天": {
		"name": "王慕天",
		"P": 2,
		"holiday": 0,
		"email": ""
	},
	"孙付荣": {
		"name": "孙付荣",
		"P": 2,
		"holiday": 0,
		"email": ""
	},
	"喻培烽": {
		"name": "喻培烽",
		"P": 2,
		"holiday": 0,
		"email": "peifeng.yu@baoz.cn"
	},
	"asionius": {
		"name": "王爱科",
		"P": 2,
		"holiday": 0,
		"email": "aike.wang@baoz.cn"
	},
	"陆恒": {
		"name": "陆恒",
		"P": 2,
		"holiday": 0,
		"email": "heng.lu@baoz.cn"
	},
	"谭学潮": {
		"name": "谭学潮",
		"P": 1,
		"holiday": 0,
		"email": ""
	},
	"龙腾跃": {
		"name": "龙腾跃",
		"P": 2,
		"holiday": 0,
		"email": "tengyue.long@baoz.cn"
	},
	"程子豪": {
		"name": "程子豪",
		"P": 2,
		"holiday": 0,
		"email": "zihao.cheng@baoz.cn"
	},
	"取小之": {
		"name": "史蓉",
		"P": 1,
		"holiday": 0,
		"email": "rong.shi@baoz.cn"
	},
	"季伟": {
		"name": "季伟",
		"P": 1,
		"holiday": 0,
		"email": "wei.ji@baoz.cn"
	},
	"霜": {
		"name": "孟志鹏",
		"P": 1,
		"holiday": 0,
		"email": "zhipeng.meng@baoz.cn"
	},
	"孙聪": {
		"name": "孙聪",
		"P": 1,
		"holiday": 0,
		"email": "cong.sun@baoz.cn"
	},
	"小美妹": {
		"name": "卢礼梅",
		"P": 1,
		"holiday": 0,
		"email": ""
	},
	"小美": {
		"name": "赵文婷",
		"P": 1,
		"holiday": 0,
		"email": "wenting.zhao@baoz.cn"
	},
	"千城墨白": {
		"name": "王锋",
		"P": 1,
		"holiday": 0,
		"email": "feng.wang@baoz.cn"
	},
	"邵德云": {
		"name": "邵德云",
		"P": 1,
		"holiday": 0,
		"email": "15195889939@163.com"
	},
	"汪嘉旻": {
		"name": "汪嘉旻",
		"P": 1,
		"holiday": 0,
		"email": "jiamin.wang@baoz.cn"
	},
	"秦书影": {
		"name": "秦书影",
		"P": 1,
		"holiday": 0,
		"email": "shuying.qin@baoz.cn"
	},
	"石梦雨": {
		"name": "石梦雨",
		"P": 1,
		"holiday": 0,
		"email": ""
	},

	"徐荣": {
		"name": "徐荣",
		"P": 1,
		"holiday": 0,
		"email": ""
	},
	"黄晓丹": {
		"name": "黄晓丹",
		"P": 1,
		"holiday": 0,
		"email": ""
	},
	"卢丹": {
		"name": "卢丹",
		"P": 1,
		"holiday": 0,
		"email": ""
	},
	"刘艳芬": {
		"name": "刘艳芬",
		"P": 1,
		"holiday": 0,
		"email": ""
	},
	"赵斌": {
		"name": "赵斌",
		"P": 1,
		"holiday": 0,
		"email": ""
	},
	"王伟杰": {
		"name": "王伟杰",
		"P": 1,
		"holiday": 0,
		"email": ""
	},
	"陈咏婷": {
		"name": "陈咏婷",
		"P": 1,
		"holiday": 0,
		"email": ""
	}
}